LICENSE
MANIFEST.in
README.rst
setup.py
jega/__init__.py
jega/loop.py
jega/patch.py
jega/six.py
jega.egg-info/PKG-INFO
jega.egg-info/SOURCES.txt
jega.egg-info/dependency_links.txt
jega.egg-info/requires.txt
jega.egg-info/top_level.txt
jega/ext/__init__.py
jega/ext/jos.py
jega/ext/jselect.py
jega/ext/jsocket.py
jega/ext/jssl.py
jega/futures/__init__.py
jega/futures/_base.py
jega/futures/_process.py
jega/futures/_thread.py
lib/c-ares/ares.h
lib/c-ares/ares__close_sockets.c
lib/c-ares/ares__get_hostent.c
lib/c-ares/ares__read_line.c
lib/c-ares/ares__timeval.c
lib/c-ares/ares_build.h
lib/c-ares/ares_config.h
lib/c-ares/ares_data.c
lib/c-ares/ares_data.h
lib/c-ares/ares_destroy.c
lib/c-ares/ares_dns.h
lib/c-ares/ares_expand_name.c
lib/c-ares/ares_free_hostent.c
lib/c-ares/ares_free_string.c
lib/c-ares/ares_getenv.h
lib/c-ares/ares_gethostbyaddr.c
lib/c-ares/ares_gethostbyname.c
lib/c-ares/ares_getnameinfo.c
lib/c-ares/ares_getopt.h
lib/c-ares/ares_init.c
lib/c-ares/ares_iphlpapi.h
lib/c-ares/ares_ipv6.h
lib/c-ares/ares_library_init.c
lib/c-ares/ares_library_init.h
lib/c-ares/ares_llist.c
lib/c-ares/ares_llist.h
lib/c-ares/ares_mkquery.c
lib/c-ares/ares_nowarn.c
lib/c-ares/ares_nowarn.h
lib/c-ares/ares_options.c
lib/c-ares/ares_parse_a_reply.c
lib/c-ares/ares_parse_aaaa_reply.c
lib/c-ares/ares_parse_ptr_reply.c
lib/c-ares/ares_platform.c
lib/c-ares/ares_platform.h
lib/c-ares/ares_private.h
lib/c-ares/ares_process.c
lib/c-ares/ares_query.c
lib/c-ares/ares_rules.h
lib/c-ares/ares_search.c
lib/c-ares/ares_send.c
lib/c-ares/ares_setup.h
lib/c-ares/ares_strcasecmp.c
lib/c-ares/ares_strcasecmp.h
lib/c-ares/ares_strdup.c
lib/c-ares/ares_strdup.h
lib/c-ares/ares_strerror.c
lib/c-ares/ares_timeout.c
lib/c-ares/ares_version.c
lib/c-ares/ares_version.h
lib/c-ares/ares_writev.c
lib/c-ares/ares_writev.h
lib/c-ares/bitncmp.c
lib/c-ares/bitncmp.h
lib/c-ares/config-win32.h
lib/c-ares/inet_net_pton.c
lib/c-ares/inet_net_pton.h
lib/c-ares/inet_ntop.c
lib/c-ares/inet_ntop.h
lib/c-ares/nameser.h
lib/c-ares/setup_once.h
lib/c-ares/windows_port.c
lib/greenlet/greenlet.h
lib/picoev/picoev.h
lib/picoev/picoev_epoll.c
src/buffer.c
