Metadata-Version: 1.1
Name: jega
Version: 0.1
Summary: Jega is a concurrent networking and cooperative multitasking library for Python3.
Home-page: https://github.com/mopemope/jega
Author: yutaka matsubara
Author-email: yutaka.matsubara@gmail.com
License: BSD
Platform: Linux
Platform: BSD
Classifier: Programming Language :: C
Classifier: Programming Language :: Python :: 3
Classifier: Programming Language :: Python :: 3.2
Classifier: Programming Language :: Python :: 3.3
Classifier: Operating System :: POSIX :: Linux
Classifier: License :: OSI Approved :: BSD License
Classifier: Topic :: Internet
Classifier: Topic :: Software Development :: Libraries :: Python Modules
Classifier: Intended Audience :: Developers
Classifier: Development Status :: 3 - Alpha
